LICENSE
MANIFEST.in
README.rst
setup.py
bee_django_mission/__init__.py
bee_django_mission/admin.py
bee_django_mission/apps.py
bee_django_mission/decorators.py
bee_django_mission/dt.py
bee_django_mission/exports.py
bee_django_mission/forms.py
bee_django_mission/http.py
bee_django_mission/models.py
bee_django_mission/signals.py
bee_django_mission/tests.py
bee_django_mission/urls.py
bee_django_mission/utils.py
bee_django_mission/views.py
bee_django_mission.egg-info/PKG-INFO
bee_django_mission.egg-info/SOURCES.txt
bee_django_mission.egg-info/dependency_links.txt
bee_django_mission.egg-info/top_level.txt
bee_django_mission/management/__init__.py
bee_django_mission/management/__init__.pyc
bee_django_mission/management/commands/__init__.py
bee_django_mission/management/commands/__init__.pyc
bee_django_mission/management/commands/init_mission_type.py
bee_django_mission/management/commands/init_mission_type.pyc
bee_django_mission/migrations/0001_initial.py
bee_django_mission/migrations/0001_initial.pyc
bee_django_mission/migrations/0002_userstage_stutas.py
bee_django_mission/migrations/0002_userstage_stutas.pyc
bee_django_mission/migrations/0003_auto_20180529_1844.py
bee_django_mission/migrations/0003_auto_20180529_1844.pyc
bee_django_mission/migrations/0004_missiontype_line_type.py
bee_django_mission/migrations/0004_missiontype_line_type.pyc
bee_django_mission/migrations/0005_auto_20180605_1631.py
bee_django_mission/migrations/0005_auto_20180605_1631.pyc
bee_django_mission/migrations/0006_userstagetfinishcount.py
bee_django_mission/migrations/0006_userstagetfinishcount.pyc
bee_django_mission/migrations/0007_auto_20180613_1555.py
bee_django_mission/migrations/0007_auto_20180613_1555.pyc
bee_django_mission/migrations/0008_customusermission.py
bee_django_mission/migrations/0008_customusermission.pyc
bee_django_mission/migrations/0009_auto_20180614_1705.py
bee_django_mission/migrations/0009_auto_20180614_1705.pyc
bee_django_mission/migrations/0010_userstage_prize_coin.py
bee_django_mission/migrations/0010_userstage_prize_coin.pyc
bee_django_mission/migrations/0011_stageprize.py
bee_django_mission/migrations/0011_stageprize.pyc
